skymantle_boto_buddy/__init__.py
skymantle_boto_buddy/cloudformation.py
skymantle_boto_buddy/dynamodb.py
skymantle_boto_buddy/logs.py
skymantle_boto_buddy/s3.py
skymantle_boto_buddy/ssm.py
skymantle_boto_buddy/stepfunctions.py
skymantle_boto_buddy/sts.py
skymantle_boto_buddy-0.3.0.dist-info/METADATA
skymantle_boto_buddy-0.3.0.dist-info/WHEEL
skymantle_boto_buddy-0.3.0.dist-info/licenses/LICENSE
skymantle_boto_buddy-0.3.0.dist-info/RECORD
