Metadata-Version: 2.3
Name: skymantle_boto_buddy
Version: 0.3.0
Summary: A wrappper for boto3 to help access and test usage of common aws services.
Project-URL: Home, https://github.com/skymantle-tech/skymantle-boto-buddy
Project-URL: Issues, https://github.com/skymantle-tech/skymantle-boto-buddy/issues
Author-email: Artin Yong-Bannayan <ayongbannayan@skymantle.com>
License:                                  Apache License
License-File: LICENSE
Classifier: Development Status :: 4 - Beta
Classifier: Intended Audience :: Developers
Classifier: License :: OSI Approved :: Apache Software License
Classifier: Programming Language :: Python
Requires-Python: >=3.11
Provides-Extra: boto
Requires-Dist: boto3; extra == 'boto'
